types_pyxdg-0.28.0.20250622.dist-info/licenses/LICENSE
xdg-stubs/BaseDirectory.pyi
xdg-stubs/Config.pyi
xdg-stubs/DesktopEntry.pyi
xdg-stubs/Exceptions.pyi
xdg-stubs/IconTheme.pyi
xdg-stubs/IniFile.pyi
xdg-stubs/Locale.pyi
xdg-stubs/METADATA.toml
xdg-stubs/Menu.pyi
xdg-stubs/MenuEditor.pyi
xdg-stubs/Mime.pyi
xdg-stubs/RecentFiles.pyi
xdg-stubs/__init__.pyi
xdg-stubs/py.typed
xdg-stubs/util.pyi
types_pyxdg-0.28.0.20250622.dist-info/METADATA
types_pyxdg-0.28.0.20250622.dist-info/WHEEL
types_pyxdg-0.28.0.20250622.dist-info/top_level.txt
types_pyxdg-0.28.0.20250622.dist-info/RECORD
